{"name":"General Payment Data Analysis","uuid":"156e91fc-504c-4ccd-8c57-f362554379a7","category":"Payment","description":"Plot monthly dollar spend in - 2013","nodes":[{"id":"1","name":"DatasetStructured","description":"This Node creates a DataFrame by reading data from HDFS, HIVE etc. The dataset has been defined earlier in Fire by using the Dataset Feature. As a user, you just have to select the Dataset of your interest.","details":"","examples":"","type":"dataset","nodeClass":"fire.nodes.dataset.NodeDatasetStructured","x":"20.6736px","y":"257.302px","fields":[{"name":"storageLevel","value":"DEFAULT","widget":"array","title":"Output Storage Level","description":"Storage Level of the Output Datasets of this Node","optionsArray":["DEFAULT","NONE","DISK_ONLY","DISK_ONLY_2","MEMORY_ONLY","MEMORY_ONLY_2","MEMORY_ONLY_SER","MEMORY_ONLY_SER_2","MEMORY_AND_DISK","MEMORY_AND_DISK_2","MEMORY_AND_DISK_SER","MEMORY_AND_DISK_SER_2","OFF_HEAP"],"required":false,"display":true,"editable":true,"disableRefresh":false},{"name":"dataset","value":"de0b65b3-9bc5-4d01-b4ca-7d189ef77b57","widget":"dataset","title":"Dataset","description":"Selected Dataset","required":false,"display":true,"editable":true,"disableRefresh":false}],"engine":"scala"},{"id":"3","name":"ColumnFilter","description":"This node creates a new DataFrame that contains only the selected columns","details":"","examples":"","type":"transform","nodeClass":"fire.nodes.etl.NodeColumnFilter","x":"204.931px","y":"268.531px","fields":[{"name":"storageLevel","value":"DEFAULT","widget":"array","title":"Output Storage Level","description":"Storage Level of the Output Datasets of this Node","optionsArray":["DEFAULT","NONE","DISK_ONLY","DISK_ONLY_2","MEMORY_ONLY","MEMORY_ONLY_2","MEMORY_ONLY_SER","MEMORY_ONLY_SER_2","MEMORY_AND_DISK","MEMORY_AND_DISK_2","MEMORY_AND_DISK_SER","MEMORY_AND_DISK_SER_2","OFF_HEAP"],"required":false,"display":true,"editable":true,"disableRefresh":false},{"name":"outputCols","value":"[\"Total_Amount_of_Payment_USDollars\",\"Date_of_Payment\"]","widget":"variables","title":"Columns","description":"Columns to be included in the output DataFrame","required":false,"display":true,"editable":true,"disableRefresh":false}],"engine":"scala"},{"id":"4","name":"FieldSplitter","description":"This node splits the string of the specified input column using the specified delimiter","details":"","examples":"","type":"transform","nodeClass":"fire.nodes.etl.NodeFieldSplitter","x":"394.188px","y":"269.83px","fields":[{"name":"storageLevel","value":"DEFAULT","widget":"array","title":"Output Storage Level","description":"Storage Level of the Output Datasets of this Node","optionsArray":["DEFAULT","NONE","DISK_ONLY","DISK_ONLY_2","MEMORY_ONLY","MEMORY_ONLY_2","MEMORY_ONLY_SER","MEMORY_ONLY_SER_2","MEMORY_AND_DISK","MEMORY_AND_DISK_2","MEMORY_AND_DISK_SER","MEMORY_AND_DISK_SER_2","OFF_HEAP"],"required":false,"display":true,"editable":true,"disableRefresh":false},{"name":"inputCol","value":"Date_of_Payment","widget":"variable","title":"Input Column","description":"input column name","datatypes":["string"],"required":false,"display":true,"editable":true,"disableRefresh":false},{"name":"outputCols","value":"Month,Date,Year","widget":"textarea_medium","title":"Output Columns","description":"new column names separed by comma\u0027,\u0027.(eg: col1,co2,col3)","required":false,"display":true,"editable":true,"disableRefresh":false},{"name":"sep","value":"/","widget":"textfield","title":"Separator","description":"separator to split the input column value(default: space)","required":false,"display":true,"editable":true,"disableRefresh":false},{"name":"onError","value":"die","widget":"array","title":"On Error","description":"","optionsArray":["die","ignore"],"required":false,"display":true,"editable":true,"disableRefresh":false}],"engine":"scala"},{"id":"7","name":"CastColumnType","description":"This node creates a new DataFrame by casting input columns with a new data type","details":"","examples":"","type":"transform","nodeClass":"fire.nodes.etl.NodeCastColumnType","x":"595.455px","y":"269.09px","fields":[{"name":"storageLevel","value":"DEFAULT","widget":"array","title":"Output Storage Level","description":"Storage Level of the Output Datasets of this Node","optionsArray":["DEFAULT","NONE","DISK_ONLY","DISK_ONLY_2","MEMORY_ONLY","MEMORY_ONLY_2","MEMORY_ONLY_SER","MEMORY_ONLY_SER_2","MEMORY_AND_DISK","MEMORY_AND_DISK_2","MEMORY_AND_DISK_SER","MEMORY_AND_DISK_SER_2","OFF_HEAP"],"required":false,"display":true,"editable":true,"disableRefresh":false},{"name":"inputCols","value":"[\"Month\"]","widget":"variables","title":"Columns","description":"Columns to be cast to new data type","required":false,"display":true,"editable":true,"disableRefresh":false},{"name":"outputColType","value":"DOUBLE","widget":"array","title":"New Data Type","description":"New data type(INTEGER, DOUBLE, STRING, LONG, SHORT)","optionsArray":["BOOLEAN","BYTE","DATE","DECIMAL","DOUBLE","FLOAT","INTEGER","LONG","SHORT","STRING","TIMESTAMP"],"required":false,"display":true,"editable":true,"disableRefresh":false},{"name":"replaceExistingCols","value":"true","widget":"array","title":"Replace Existing Cols","description":"Whether to replace existing columns or create new ones","optionsArray":["true","false"],"required":false,"display":true,"editable":true,"disableRefresh":false}],"engine":"scala"},{"id":"9","name":"SQL","description":"This node runs the given SQL on the incoming DataFrame","details":"","examples":"","type":"transform","nodeClass":"fire.nodes.etl.NodeSQL","x":"787.438px","y":"269.038px","fields":[{"name":"storageLevel","value":"DEFAULT","widget":"array","title":"Output Storage Level","description":"Storage Level of the Output Datasets of this Node","optionsArray":["DEFAULT","NONE","DISK_ONLY","DISK_ONLY_2","MEMORY_ONLY","MEMORY_ONLY_2","MEMORY_ONLY_SER","MEMORY_ONLY_SER_2","MEMORY_AND_DISK","MEMORY_AND_DISK_2","MEMORY_AND_DISK_SER","MEMORY_AND_DISK_SER_2","OFF_HEAP"],"required":false,"display":true,"editable":true,"disableRefresh":false},{"name":"tempTable","value":"temptable","widget":"textfield","title":"Temp Table","description":"Temp Table Name to be used","required":false,"display":true,"editable":true,"disableRefresh":false},{"name":"sql","value":"select temptable.Month, sum(Total_Amount_of_Payment_USDollars)as Total_Dollars from temptable group by Month order by Month","widget":"textarea_medium","title":"SQL","description":"SQL to be run","required":false,"display":true,"editable":true,"disableRefresh":false},{"name":"outputColNames","value":"[\"Month\",\"Total_Dollars\"]","widget":"schema_col_names","title":"Output Column Names","description":"Name of the Output Columns","required":false,"display":true,"editable":true,"disableRefresh":false},{"name":"outputColTypes","value":"[\"DOUBLE\",\"DOUBLE\"]","widget":"schema_col_types","title":"Output Column Types","description":"Data Type of the Output Columns","required":false,"display":true,"editable":true,"disableRefresh":false},{"name":"outputColFormats","value":"[\"\",\"\"]","widget":"schema_col_formats","title":"Output Column Formats","description":"Format of the Output Columns","required":false,"display":true,"editable":true,"disableRefresh":false}],"engine":"scala"},{"id":"12","name":"PrintNRows","description":"Prints the specified number of records in the DataFrame. It is useful for seeing intermediate output","details":"","examples":"","type":"transform","nodeClass":"fire.nodes.util.NodePrintFirstNRows","x":"1003.43px","y":"356.076px","fields":[{"name":"storageLevel","value":"DEFAULT","widget":"array","title":"Output Storage Level","description":"Storage Level of the Output Datasets of this Node","optionsArray":["DEFAULT","NONE","DISK_ONLY","DISK_ONLY_2","MEMORY_ONLY","MEMORY_ONLY_2","MEMORY_ONLY_SER","MEMORY_ONLY_SER_2","MEMORY_AND_DISK","MEMORY_AND_DISK_2","MEMORY_AND_DISK_SER","MEMORY_AND_DISK_SER_2","OFF_HEAP"],"required":false,"display":true,"editable":true,"disableRefresh":false},{"name":"title","value":"Row Values","widget":"textfield","title":"Title","required":false,"display":true,"editable":true,"disableRefresh":false},{"name":"n","value":"10","widget":"text